atoMEC/__init__.py
atoMEC/check_inputs.py
atoMEC/config.py
atoMEC/convergence.py
atoMEC/mathtools.py
atoMEC/models.py
atoMEC/numerov.py
atoMEC/staticKS.py
atoMEC/unitconv.py
atoMEC/writeoutput.py
atoMEC/xc.py
atoMEC/postprocess/__init__.py
atoMEC/postprocess/conductivity.py
atoMEC/postprocess/localization.py
atoMEC/postprocess/pressure.py
atoMEC-1.4.0.dist-info/LICENSE
atoMEC-1.4.0.dist-info/METADATA
atoMEC-1.4.0.dist-info/WHEEL
atoMEC-1.4.0.dist-info/top_level.txt
atoMEC-1.4.0.dist-info/RECORD
