Metadata-Version: 2.1
Name: atoMEC
Version: 1.4.0
Summary: KS-DFT average-atom code
Home-page: https://github.com/atomec-project/atoMEC
Author: Tim Callow et al.
Author-email: t.callow@hzdr.de
License: BSD 3-Clause License
Requires-Python: >=3.6
License-File: LICENSE
Requires-Dist: numpy >=1.20.3
Requires-Dist: scipy >=1.6.3
Requires-Dist: mendeleev >=0.7.0
Requires-Dist: tabulate >=0.8.9
Requires-Dist: joblib >=1.0.1
Provides-Extra: dev
Requires-Dist: bump2version ; extra == 'dev'
Provides-Extra: docs
Requires-Dist: docutils ==0.18.1 ; extra == 'docs'
Requires-Dist: myst-parser ==2.0.0 ; extra == 'docs'
Requires-Dist: Sphinx ==7.2.6 ; extra == 'docs'
Requires-Dist: sphinx-rtd-theme ==1.3.0 ; extra == 'docs'
Provides-Extra: tests
Requires-Dist: pytest ==7.1.3 ; extra == 'tests'
Requires-Dist: pytest-cov ==4.0.0 ; extra == 'tests'
Requires-Dist: pytest-lazy-fixture ==0.6.3 ; extra == 'tests'
Requires-Dist: pytest-random-order ==1.0.4 ; extra == 'tests'
